LICENSE
amplitude_python_sdk/__init__.py
amplitude_python_sdk/common/__init__.py
amplitude_python_sdk/common/clients.py
amplitude_python_sdk/common/exceptions.py
amplitude_python_sdk/common/models.py
amplitude_python_sdk/common/utils.py
amplitude_python_sdk/integration_tests/v1/test_identify.py
amplitude_python_sdk/integration_tests/v2/clients/conftest.py
amplitude_python_sdk/integration_tests/v2/clients/test_chart_annotations_client.py
amplitude_python_sdk/integration_tests/v2/clients/test_event_client.py
amplitude_python_sdk/integration_tests/v2/clients/test_releases_client.py
amplitude_python_sdk/tests/common/test_models.py
amplitude_python_sdk/tests/common/test_utils.py
amplitude_python_sdk/tests/v1/models/test_identify.py
amplitude_python_sdk/tests/v1/test_client.py
amplitude_python_sdk/tests/v2/clients/test_chart_annotations_client.py
amplitude_python_sdk/tests/v2/clients/test_event_client.py
amplitude_python_sdk/tests/v2/clients/test_releases_client.py
amplitude_python_sdk/tests/v2/models/test_releases.py
amplitude_python_sdk/v1/__init__.py
amplitude_python_sdk/v1/client.py
amplitude_python_sdk/v1/models/__init__.py
amplitude_python_sdk/v1/models/identify.py
amplitude_python_sdk/v1/routes.py
amplitude_python_sdk/v2/__init__.py
amplitude_python_sdk/v2/clients/__init__.py
amplitude_python_sdk/v2/clients/chart_annotations_client.py
amplitude_python_sdk/v2/clients/event_client.py
amplitude_python_sdk/v2/clients/releases_client.py
amplitude_python_sdk/v2/exceptions/event.py
amplitude_python_sdk/v2/models/__init__.py
amplitude_python_sdk/v2/models/charts.py
amplitude_python_sdk/v2/models/event/__init__.py
amplitude_python_sdk/v2/models/event/api.py
amplitude_python_sdk/v2/models/event/base.py
amplitude_python_sdk/v2/models/event/options.py
amplitude_python_sdk/v2/models/releases.py
amplitude_python_sdk/v2/routes.py
amplitude_python_sdk-0.3.0.dist-info/LICENSE
amplitude_python_sdk-0.3.0.dist-info/METADATA
amplitude_python_sdk-0.3.0.dist-info/WHEEL
amplitude_python_sdk-0.3.0.dist-info/RECORD
