Metadata-Version: 2.1
Name: amplitude-python-sdk
Version: 0.3.0
Summary: Client for the Amplitude HTTP V1 and V2 API (https://developers.amplitude.com/docs).
Home-page: https://github.com/researchrabbit/amplitude-python-sdk
License: MIT
Author: Krishnan Chandra
Author-email: krishnan.chandra@gmail.com
Requires-Python: >=3.8,<4.0
Classifier: License :: OSI Approved :: MIT License
Classifier: Programming Language :: Python :: 3
Classifier: Programming Language :: Python :: 3.8
Classifier: Programming Language :: Python :: 3.9
Classifier: Programming Language :: Python :: 3.10
Classifier: Programming Language :: Python :: 3.11
Classifier: Programming Language :: Python :: 3.12
Requires-Dist: pydantic (>=2.5.0,<3.0.0)
Requires-Dist: requests (>=2.25.1,<3.0.0)
Project-URL: Repository, https://github.com/researchrabbit/amplitude-python-sdk
